advanced_sorting_algorithms/__init__.py
advanced_sorting_algorithms/advanced_sorting_algorithms.py
advanced_sorting_algorithms/advanced_sorting_algorithms.pyi
advanced_sorting_algorithms-0.1.4.dist-info/LICENSE
advanced_sorting_algorithms-0.1.4.dist-info/METADATA
advanced_sorting_algorithms-0.1.4.dist-info/WHEEL
advanced_sorting_algorithms-0.1.4.dist-info/top_level.txt
advanced_sorting_algorithms-0.1.4.dist-info/RECORD
