Metadata-Version: 2.1
Name: advanced_sorting_algorithms
Version: 0.1.4
Summary: just some sorting algorithms and algorithms part for you
Home-page: https://github.com/Daniil2321/sorting_algorithms
Author: Hryharovich Daniil
Author-email: drink.wtoroy@gmail.com
Classifier: Programming Language :: Python :: 3
Classifier: License :: OSI Approved :: MIT License
Classifier: Operating System :: OS Independent
Requires-Python: >=3.6
License-File: LICENSE
